{
  "_fv": 18,
  "_type": "armor",
  "definition": {
    "enableHelmet": true,
    "textureHelmet": "sb_head",
    "enableBody": true,
    "textureBody": "sb_torso",
    "enableLeggings": true,
    "textureLeggings": "sb_pants",
    "enableBoots": true,
    "textureBoots": "sb_boots",
    "creativeTab": {
      "value": "CUSTOM:FNAFItems"
    },
    "armorTextureFile": "springbonniesuit_",
    "helmetName": "Spring Bonnie Head",
    "bodyName": "Spring Lock Suit Body",
    "leggingsName": "Spring Lock Suit Legs",
    "bootsName": "Spring Lock Suit Boots",
    "helmetSpecialInfo": [],
    "bodySpecialInfo": [],
    "leggingsSpecialInfo": [],
    "bootsSpecialInfo": [],
    "helmetModelName": "ModelSpring_Bonnie_Suit",
    "helmetModelPart": "Helmet",
    "helmetModelTexture": "spring_bonnie_suit.png",
    "bodyModelName": "ModelSpring_Bonnie_Suit",
    "bodyModelPart": "Chestplate",
    "armsModelPartL": "LArm",
    "armsModelPartR": "RArm",
    "bodyModelTexture": "spring_bonnie_suit.png",
    "leggingsModelName": "ModelSpring_Bonnie_Suit",
    "leggingsModelPartL": "LLeg",
    "leggingsModelPartR": "RLeg",
    "leggingsModelTexture": "spring_bonnie_suit.png",
    "bootsModelName": "ModelSpring_Bonnie_Suit",
    "bootsModelPartL": "LBoot",
    "bootsModelPartR": "RBoot",
    "bootsModelTexture": "spring_bonnie_suit.png",
    "maxDamage": 0,
    "damageValueHelmet": 0,
    "damageValueBody": 0,
    "damageValueLeggings": 0,
    "damageValueBoots": 0,
    "enchantability": 9,
    "toughness": 0.0,
    "knockbackResistance": 0.0,
    "equipSound": {
      "value": ""
    },
    "repairItems": []
  }
}